setup.cfg
setup.py
osm_opening_hours.egg-info/PKG-INFO
osm_opening_hours.egg-info/SOURCES.txt
osm_opening_hours.egg-info/dependency_links.txt
osm_opening_hours.egg-info/top_level.txt
osm_time/__init__.py
osm_time/opening_hours.py