Metadata-Version: 1.1
Name: osm-opening-hours
Version: 0.1.1
Summary: Tools to parse opening hours format from OpenStreetMap.
Home-page: https://github.com/k-nut/osm-opening-hours
Author: Martin Filliau
Author-email: martin@filliau.com
License: UNKNOWN
Platform: UNKNOWN
Classifier: Operating System :: OS Independent
Classifier: Programming Language :: Python
